mcp_server_vegalite/__init__.py
mcp_server_vegalite/server.py
mseep_mcp_server_vegalite-0.0.5.dist-info/METADATA
mseep_mcp_server_vegalite-0.0.5.dist-info/WHEEL
mseep_mcp_server_vegalite-0.0.5.dist-info/entry_points.txt
mseep_mcp_server_vegalite-0.0.5.dist-info/top_level.txt
mseep_mcp_server_vegalite-0.0.5.dist-info/RECORD
